reification/__init__.py
reification/abs.py
reification/py.typed
reification/utils.py
reification-1.0.12.dist-info/licenses/LICENSE
reification-1.0.12.dist-info/METADATA
reification-1.0.12.dist-info/WHEEL
reification-1.0.12.dist-info/top_level.txt
reification-1.0.12.dist-info/RECORD
