Metadata-Version: 2.4
Name: reification
Version: 1.0.12
Summary: Reified generics in Python to get type parameters at runtime
Maintainer-email: curegit <contact@curegit.jp>
License-Expression: WTFPL
Project-URL: homepage, https://github.com/curegit/reification
Project-URL: repository, https://github.com/curegit/reification.git
Keywords: typing,generics,parametric polymorphism,reification,type parameter,reflection
Classifier: Programming Language :: Python :: 3 :: Only
Classifier: Operating System :: OS Independent
Classifier: Intended Audience :: Developers
Classifier: Topic :: Software Development :: Libraries :: Python Modules
Classifier: Typing :: Typed
Requires-Python: >=3.12
License-File: LICENSE
Provides-Extra: dev
Requires-Dist: pip; extra == "dev"
Requires-Dist: build; extra == "dev"
Requires-Dist: twine; extra == "dev"
Requires-Dist: black; extra == "dev"
Requires-Dist: mypy; extra == "dev"
Requires-Dist: coverage; extra == "dev"
Dynamic: license-file
